slideio/__init__.py
slideio/core/__init__.py
slideio/core/libs/concrt140.dll
slideio/core/libs/glog.dll
slideio/core/libs/msvcp140.dll
slideio/core/libs/msvcp140_1.dll
slideio/core/libs/msvcp140_2.dll
slideio/core/libs/msvcp140_codecvt_ids.dll
slideio/core/libs/slideio-afi.dll
slideio/core/libs/slideio-base.dll
slideio/core/libs/slideio-converter.dll
slideio/core/libs/slideio-core.dll
slideio/core/libs/slideio-czi.dll
slideio/core/libs/slideio-dcm.dll
slideio/core/libs/slideio-gdal.dll
slideio/core/libs/slideio-imagetools.dll
slideio/core/libs/slideio-ndpi.dll
slideio/core/libs/slideio-pke.dll
slideio/core/libs/slideio-scn.dll
slideio/core/libs/slideio-svs.dll
slideio/core/libs/slideio-transformer.dll
slideio/core/libs/slideio-vsi.dll
slideio/core/libs/slideio-zvi.dll
slideio/core/libs/slideio.dll
slideio/core/libs/slideiopybind.cp37-win_amd64.pyd
slideio/core/libs/vccorlib140.dll
slideio/core/libs/vcruntime140.dll
slideio/core/libs/vcruntime140_1.dll
slideio/wrappers/__init__.py
slideio/wrappers/py_slideio.py
slideio-2.7.3.data/data/requirements-dev.txt
slideio-2.7.3.dist-info/LICENSE.md
slideio-2.7.3.dist-info/METADATA
slideio-2.7.3.dist-info/WHEEL
slideio-2.7.3.dist-info/top_level.txt
slideio-2.7.3.dist-info/RECORD
