Metadata-Version: 2.1
Name: slideio
Version: 2.7.3
Summary: Reading of medical images
Author: Stanislav Melnikov
Author-email: stanislav.melnikov@gmail.com
Project-URL: Documentation, http://slideio.com
Project-URL: Source Code, https://github.com/Booritas/slideio
Keywords: images,pathology,tissue,medical,czi,svs,afi,scn,ndpi
Classifier: Development Status :: 5 - Production/Stable
Classifier: Intended Audience :: Science/Research
Classifier: License :: OSI Approved :: BSD License
Classifier: Topic :: Scientific/Engineering
Classifier: Topic :: Scientific/Engineering :: Bio-Informatics
Classifier: Topic :: Scientific/Engineering :: Image Recognition
Classifier: Topic :: Scientific/Engineering :: Medical Science Apps.
Classifier: Programming Language :: Python :: 3.7
Classifier: Programming Language :: Python :: 3.8
Classifier: Programming Language :: Python :: 3.9
Classifier: Programming Language :: Python :: 3.10
Classifier: Programming Language :: Python :: 3.11
Classifier: Programming Language :: Python :: 3.12
License-File: LICENSE.md
Requires-Dist: numpy
